influxdb_logging/__init__.py
influxdb_logging/handler.py
influxdb_logging-2.0.0.dist-info/DESCRIPTION.rst
influxdb_logging-2.0.0.dist-info/METADATA
influxdb_logging-2.0.0.dist-info/RECORD
influxdb_logging-2.0.0.dist-info/WHEEL
influxdb_logging-2.0.0.dist-info/metadata.json
influxdb_logging-2.0.0.dist-info/top_level.txt
