Metadata-Version: 2.0
Name: influxdb-logging
Version: 2.0.0
Summary: InfluxDB logging handlers
Home-page: https://github.com/gsr-zug/influxdb_logging
Author: Jefferson Heard
Author-email: jheard@teamworks.com
License: MIT
Platform: UNKNOWN
Classifier: Programming Language :: Python :: 3
Classifier: Development Status :: 3 - Alpha
Classifier: Topic :: Software Development :: Build Tools
Classifier: Topic :: System :: Logging
Requires-Python: >=3
Requires-Dist: influxdb (==5.0.0)
Requires-Dist: pytest (==3.3.2)
Requires-Dist: pytest-cov (==2.5.1)
